chiquifork-0.1.0.dist-info/METADATA
chiquifork-0.1.0.dist-info/WHEEL
chiquifork/wit_gen.py
chiquifork/query.py
chiquifork/dsl.py
chiquifork/__init__.py
chiquifork/cb.py
chiquifork/expr.py
chiquifork/util.py
chiquifork/chiquito_ast.py
chiquifork/rust_chiquito.cpython-311-i386-linux-gnu.so
chiquifork-0.1.0.dist-info/RECORD
